README.md
setup.cfg
setup.py
HCP_DataProcessor/__init__.py
HCP_DataProcessor/main.py
HCP_DataProcessor/script.py
HCP_DataProcessor.egg-info/PKG-INFO
HCP_DataProcessor.egg-info/SOURCES.txt
HCP_DataProcessor.egg-info/dependency_links.txt
HCP_DataProcessor.egg-info/requires.txt
HCP_DataProcessor.egg-info/top_level.txt
HCP_DataProcessor/Data_Process/Data_Process.py
HCP_DataProcessor/Data_Process/_PCA_Filter.py
HCP_DataProcessor/Data_Process/__init__.py
HCP_DataProcessor/Data_Process/_correlation_matrix_collector.py