Metadata-Version: 1.1
Name: HCP-DataProcessor
Version: 0.0.6
Summary: HCP_DataProcessor.
Home-page: https://github.com/xinyuwang1209/HCP_DataProcessor.git
Author: Xinyu Wang
Author-email: xinyuwang1209@gmail.com
License: UNKNOWN
Keywords: Xinyu, xinyu, pypi, package, rpki
Platform: any
Classifier: Environment :: Console
Classifier: Intended Audience :: Developers
Classifier: License :: OSI Approved :: MIT License
Classifier: Operating System :: OS Independent
Classifier: Programming Language :: Python
Classifier: Programming Language :: Python :: 3
